claranet_tfwrapper/__init__.py
claranet_tfwrapper/azure.py
claranet_tfwrapper/utils.py
claranet_tfwrapper-14.0.3.dist-info/METADATA
claranet_tfwrapper-14.0.3.dist-info/WHEEL
claranet_tfwrapper-14.0.3.dist-info/entry_points.txt
claranet_tfwrapper-14.0.3.dist-info/licenses/LICENSE
claranet_tfwrapper-14.0.3.dist-info/RECORD
