Metadata-Version: 2.4
Name: claranet-tfwrapper
Version: 14.0.3
Summary: Claranet's `tfwrapper` is a wrapper for [Terraform](https://www.terraform.io/) implemented in python which aims to simplify Terraform usage and enforce best practices
Project-URL: homepage, https://github.com/claranet/tfwrapper
License: Mozilla Public License Version 2.0
License-File: LICENSE
Keywords: terraform,wrapper
Classifier: Development Status :: 5 - Production/Stable
Classifier: Intended Audience :: Developers
Classifier: Intended Audience :: Information Technology
Classifier: Intended Audience :: System Administrators
Classifier: License :: OSI Approved :: Mozilla Public License 2.0 (MPL 2.0)
Classifier: Programming Language :: Python :: 3
Classifier: Programming Language :: Python :: 3.9
Classifier: Programming Language :: Python :: 3.10
Classifier: Programming Language :: Python :: 3.11
Classifier: Programming Language :: Python :: 3.12
Classifier: Programming Language :: Python :: 3.13
Classifier: Programming Language :: Python :: 3.14
Classifier: Topic :: System :: Systems Administration
Classifier: Topic :: Utilities
Requires-Python: <4.0,>=3.9
Requires-Dist: argcomplete<4.0
Requires-Dist: boto3<2.0.0,>=1.17.94
Requires-Dist: cachecontrol[filecache]<0.15.0,>=0.14.0
Requires-Dist: colorlog<7.0.0,>=5.0.1
Requires-Dist: jinja2<4.0.0,>=3.0.1
Requires-Dist: lockfile<0.13.0,>=0.12.2
Requires-Dist: natsort<9.0.0,>=7.1.1
Requires-Dist: packaging<26,>=25
Requires-Dist: pyyaml<7.0.0,>=6.0.1
Requires-Dist: requests<3.0.0,>=2.25.1
Requires-Dist: schema<0.8.0,>=0.7.4
Requires-Dist: semver<4.0.0,>=3.0.1
Requires-Dist: termcolor<3.2,>=3.1
